{
  "$schema": "http://json-schema.org/draft-04/schema#",
  "type": "object",
  "properties": {
    "system_url": {
      "type": "string",
      "title": "Marketing Instance URL",
      "description": "The base URL of the SAP Marketing Cloud instance you want to register. For example, https://marketing.organization.com"
    },
    "basic_user": {
      "type": "string",
      "title": "Basic Auth Username",
      "description": "The username for the Communication User. The Communication User must already exist in SAP Marketing Cloud and used for all of the Communication Arrangements (used to expose APIs) you want to register in the Extension Factory"
    },
    "basic_password": {
      "type": "string",
      "title": "Basic Auth Password",
      "description": "The password for the Communication User in SAP Marketing Cloud"
    },
    "oauth_client_id": {
      "type": "string",
      "title": "Oauth2 client_id",
      "description": "The OAuth 2.0 Client ID for sending the MQTT events. The OAuth 2.0 credentials are required to configure the Communication Scenario"
    },
    "oauth_client_secret": {
      "type": "string",
      "title": "OAuth2 client_secret",
      "description": "The OAuth 2.0 Client Secret for sending the MTTQ events"
    },
    "application_name": {
      "type": "string",
      "title": "Application Name",
      "description": "The name of the Application CR where the ODATA services and the event catalog should be registered for consumption"
    },
    "cluster_domain": {
      "type": "string",
      "title": "Cluster Domain",
      "description": "The domain of the cluster. For example, `demo.kyma.cx`"
    }
  },
  "required": [
    "system_url",
    "basic_user",
    "basic_password",
    "oauth_client_id",
    "oauth_client_secret",
    "application_name",
    "cluster_domain"
  ]
}